{
  "sectionTitle": "What We Do",
  "sectionSubtitle": "Technology Solutions That Drive Results.",
  "services": [
    {
      "title": "Custom Software Development",
      "description": "We build custom software that brings your ideas to life. Whether it is a web app, an internal tool, or something completely new, we help you go from concept to launch.",
      "slug": "custom-software"
    },
    {
      "title": "Business Process Automation",
      "description": "We help automate the work that slows you down so your team can focus on higher value work. The result is smoother operations, fewer mistakes, and more time to grow.",
      "slug": "business-automation"
    },
    {
      "title": "Web Design & Development",
      "description": "We design and build modern websites that look great, load fast, and make it easier for visitors to become customers.",
      "slug": "web-design"
    }
  ]
}
